behave_teamcity/__init__.py
behave_teamcity-0.1.25.dist-info/DESCRIPTION.rst
behave_teamcity-0.1.25.dist-info/METADATA
behave_teamcity-0.1.25.dist-info/RECORD
behave_teamcity-0.1.25.dist-info/WHEEL
behave_teamcity-0.1.25.dist-info/metadata.json
behave_teamcity-0.1.25.dist-info/pbr.json
behave_teamcity-0.1.25.dist-info/top_level.txt
