Metadata-Version: 2.0
Name: behave-teamcity
Version: 0.1.25
Summary: TeamCity test report formatter for behave
Home-page: https://github.com/iljabauer/behave-teamcity
Author: Ilja Bauer
Author-email: i.bauer@cuescience.de
License: MIT
Download-URL: https://github.com/iljabauer/behave-teamcity/releases/tag/0.1.23
Keywords: testing,behave,teamcity,formatter,report
Platform: UNKNOWN
Classifier: Development Status :: 5 - Production/Stable
Classifier: Intended Audience :: Developers
Classifier: License :: OSI Approved :: MIT License
Classifier: Topic :: Software Development :: Testing
Classifier: Topic :: Software Development :: Build Tools
Classifier: Topic :: Utilities
Requires-Dist: behave (>=1.2.5,<=1.3)
Requires-Dist: teamcity-messages
